setup.py
rlagents/__init__.py
rlagents/mc.py
rlagents/ql.py
rlagents/tools.py
rlagents.egg-info/PKG-INFO
rlagents.egg-info/SOURCES.txt
rlagents.egg-info/dependency_links.txt
rlagents.egg-info/not-zip-safe
rlagents.egg-info/requires.txt
rlagents.egg-info/top_level.txt