Metadata-Version: 1.0
Name: rlagents
Version: 0.0.15
Summary: Reinforcement Learning Agents
Home-page: http://github.com/theSage21/rlagents
Author: Arjoonn Sharma
Author-email: arjoonn.94@gmail.com
License: MIT
Keywords: rlagents,reinforcement,learning
Platform: UNKNOWN
